{
  "$schema": "http://json-schema.org/draft-07/schema#",
  "$id": "BillingCycleSpecification.schema.json",
  "title": "BillingCycleSpecification",
  "definitions": {
    "BillingCycleSpecification": {
      "$id": "#BillingCycleSpecification",
      "description": "A detailed description of when to initiate a billing cycle and the various sub steps of a billing cycle.",
      "type": "object",
      "required": [
        "name"
      ],
      "properties": {
        "billingDateShift": {
          "type": "integer",
          "description": "An offset of a billing/settlement date. The offset is expressed as number of days with regard to the start of the billing/settlement period."
        },
        "billingPeriod": {
          "type": "string",
          "description": "A billing time period. It can be recurring, for example: week, month, quarter of year, year ."
        },
        "chargeDateOffset": {
          "type": "integer",
          "description": "An offset of a date through which charges previously received by the billing system will appear on the bill. The offset is expressed as number of days with regard to the start of the BillingPeriod."
        },
        "creditDateOffset": {
          "type": "integer",
          "description": "An offset of a date through which credits previously received by the billing system will appear on the bill. The offset is expressed as number of days with regard to the start of the BillingPeriod."
        },
        "description": {
          "type": "string",
          "description": "An explanation regarding this billing cycle specification"
        },
        "frequency": {
          "type": "string",
          "description": "Frequency of the billing cycle (monthly for instance)"
        },
        "href": {
          "type": "string",
          "description": "Reference of the billing cycle specification"
        },
        "id": {
          "type": "string",
          "description": "Unique identifier of the billing cycle specification"
        },
        "mailingDateOffset": {
          "type": "integer",
          "description": "An offset of a customer bill mailing date. The offset is expressed as number of days with regard to the start of the BillingPeriod."
        },
        "name": {
          "type": "string",
          "description": "A short descriptive name"
        },
        "paymentDueDateOffset": {
          "type": "integer",
          "description": "An offset of a payment due date. The offset is expressed as number of days with regard to the start of the BillingPeriod."
        },
        "validFor": {
          "$ref": "../Common/TimePeriod.schema.json#TimePeriod",
          "description": "The period for which the billing specification cycle is valid"
        }
      },
      "allOf": [
        {
          "$ref": "../Common/Entity.schema.json#Entity"
        }
      ]
    }
  }
}
