{
  "$schema": "http://json-schema.org/draft-07/schema#",
  "$id": "LoyaltyAccount.schema.json",
  "title": "LoyaltyAccount",
  "definitions": {
    "LoyaltyAccount": {
      "$id": "#LoyaltyAccount",
      "description": "A loyalty account, containing loyalty balances.",
      "type": "object",
      "properties": {
        "id": {
          "type": "string",
          "description": "Unique identifier for the account."
        },
        "href": {
          "type": "string",
          "description": "A reference to the loyalty members loyalty account."
        },
        "loyaltyProgramProduct": {
          "$ref": "../Product/LoyaltyProgramProductRef.schema.json#LoyaltyProgramProductRef"
        }
      }
    }
  }
}
