{
  "$schema": "http://json-schema.org/draft-07/schema#",
  "$id": "ConstraintRef.schema.json",
  "title": "ConstraintRef",
  "definitions": {
    "ConstraintRef": {
      "$id": "#ConstraintRef",
      "type": "object",
      "description": "Constraint reference. The Constraint resource represents a policy/rule applied to an entity or entity spec.",
      "properties": {
        "version": {
          "type": "string",
          "description": "constraint version"
        }
      },
      "allOf": [
        {
          "$ref": "../Common/EntityRef.schema.json#/definitions/EntityRef"
        }
      ]
    }
  }
}
