{
  "$schema": "http://json-schema.org/draft-07/schema#",
  "$id": "LocationCharacteristic.schema.json",
  "title": "LocationCharacteristic",
  "definitions": {
    "LocationCharacteristic": {
      "$id": "#LocationCharacteristic",
      "description": "Name/value pairs, used to extra characterized the Area (e.g. if a standard\ncode set has been defined for the GeographicArea type, etc.)",
      "type": "object",
      "properties": {
        "name": {
          "type": "string"
        },
        "value": {
          "type": "string"
        }
      },
      "allOf": [
        {
          "$ref": "../Common/Entity.schema.json#Entity"
        }
      ]
    }
  }
}
